urbanicola_data/__init__.py
urbanicola_data/transformations.py
urbanicola_data-0.0.4.dist-info/LICENSE
urbanicola_data-0.0.4.dist-info/WHEEL
urbanicola_data-0.0.4.dist-info/METADATA
urbanicola_data-0.0.4.dist-info/RECORD
