Metadata-Version: 2.1
Name: urbanicola_data
Version: 0.0.4
Summary: A module with type of data base
Home-page: https://github.com/nepito/urbanicola_data
Author: NIES
Author-email: nepo@nies.futbol
Requires-Python: >=3.9
Classifier: License :: OSI Approved :: GNU General Public License v3 or later (GPLv3+)
Requires-Dist: pydantic
